lgblkb_navigation/base_geometry/geom_utils.py
lgblkb_navigation/base_geometry/line_utils.py
lgblkb_navigation/base_geometry/point_utils.py
lgblkb_navigation/base_geometry/poly_utils.py
lgblkb_navigation/boustrophedon_case_1.py
lgblkb_navigation/deap_1.py
lgblkb_navigation/deap_2.py
lgblkb_navigation/dubins_1.py
lgblkb_navigation/field_geometry/field_utils.py
lgblkb_navigation/global_support.py
lgblkb_navigation/gym_workout.py
lgblkb_navigation/katana_case.py
lgblkb_navigation/navi_2.py
lgblkb_navigation/poly2trap.py
lgblkb_navigation/qweqwe.py
lgblkb_navigation/seidel.py
lgblkb_navigation/the_main.py
lgblkb_navigation/utils/google_way.py
lgblkb_navigation/vis_utils.py
lgblkb_navigation-0.1.20.dist-info/WHEEL
lgblkb_navigation-0.1.20.dist-info/METADATA
lgblkb_navigation-0.1.20.dist-info/RECORD
